blurhash_pyside/_wrapper.py
blurhash_pyside/_qt.py
blurhash_pyside/_core.pyi
blurhash_pyside/__init__.py
blurhash_pyside/py.typed
blurhash_pyside/_core.cpython-311-darwin.so
blurhash_pyside/errors.py
blurhash_pyside-1.0.0.dist-info/RECORD
blurhash_pyside-1.0.0.dist-info/WHEEL
blurhash_pyside-1.0.0.dist-info/METADATA
blurhash_pyside-1.0.0.dist-info/licenses/LICENSE
