Metadata-Version: 2.1
Name: blurhash-pyside
Version: 1.0.0
Summary: Encode or Decode Blurhash strings in a PySide2/6 project.
Keywords: pyside2,pyside6,burhash
Author-Email: Leo Covarrubias <leo@leocov.com>
Classifier: Development Status :: 4 - Beta
Classifier: Programming Language :: Python
Classifier: Programming Language :: Python :: 3.9
Classifier: Programming Language :: Python :: 3.10
Classifier: Programming Language :: Python :: 3.11
Classifier: Programming Language :: Python :: 3.12
Project-URL: Documentation, https://github.com/leocov-dev/blurhash-pyside#readme
Project-URL: Issues, https://github.com/leocov-dev/blurhash-pyside/issues
Project-URL: Source, https://github.com/leocov-dev/blurhash-pyside
Project-URL: Releases, https://github.com/leocov-dev/blurhash-pyside/releases
Requires-Python: >=3.9.1
Provides-Extra: test
Requires-Dist: pytest; extra == "test"
Requires-Dist: opencv-python; extra == "test"
Requires-Dist: scikit-image; extra == "test"
